instabase_env/__init__.py
instabase_env-0.3.0.dist-info/WHEEL
instabase_env-0.3.0.dist-info/METADATA
instabase_env-0.3.0.dist-info/RECORD
