Metadata-Version: 2.1
Name: instabase-env
Version: 0.3.0
Summary: 
Author: Arjoonn Sharma
Author-email: arjoonn.sharma@instabase.com
Requires-Python: ==3.7.2
Classifier: Programming Language :: Python :: 3
Requires-Dist: Pillow (==8.1.2)
Requires-Dist: PyPDF2 (==1.26.0)
Requires-Dist: XlsxWriter (==1.0.2)
Requires-Dist: beautifulsoup4 (==4.6.3)
Requires-Dist: dateparser (==0.7.0)
Requires-Dist: nltk (==3.4.5)
Requires-Dist: numpy (==1.16.5)
Requires-Dist: opencv-contrib-python (==3.4.2.17)
Requires-Dist: pandas (==1.1.0)
Requires-Dist: pdfkit (==0.6.1)
Requires-Dist: regex (==2018.01.10)
Requires-Dist: requests (==2.22.0)
Requires-Dist: scikit-image (==0.16.2)
Requires-Dist: scikit-learn (==0.21.3)
Requires-Dist: scipy (==1.3.1)
Requires-Dist: spacy (==2.3.2)
Requires-Dist: xlwt (==1.3.0)
